README.rst
pyvkoauth.py
setup.py
pyvkoauth.egg-info/PKG-INFO
pyvkoauth.egg-info/SOURCES.txt
pyvkoauth.egg-info/dependency_links.txt
pyvkoauth.egg-info/requires.txt
pyvkoauth.egg-info/top_level.txt