Metadata-Version: 1.1
Name: pyvkoauth
Version: 0.9
Summary: OAuth authentification for vk.com
Home-page: https://bitbucket.org/cordalace/pyvkoauth
Author: Azat Kurbanov
Author-email: cordalace@gmail.com
License: Apache License 2.0
Keywords: vkontakte vk oauth auth browserless
Platform: UNKNOWN
Classifier: Development Status :: 3 - Alpha
Classifier: Intended Audience :: Developers
Classifier: License :: OSI Approved :: Apache Software License
Classifier: Natural Language :: Russian
Classifier: Programming Language :: Python :: 2.7
Classifier: Topic :: Software Development :: Libraries :: Python Modules
Classifier: Topic :: Internet :: WWW/HTTP :: Session
